param_helper/__init__.py
param_helper-1.1.1.dist-info/METADATA
param_helper-1.1.1.dist-info/WHEEL
param_helper-1.1.1.dist-info/entry_points.txt
param_helper-1.1.1.dist-info/top_level.txt
param_helper-1.1.1.dist-info/RECORD
