Metadata-Version: 2.1
Name: param-helper
Version: 1.1.1
Summary: UNKNOWN
Home-page: https://github.com/EvATive7/param-helper
Author: EvATive7
Author-email: 
License: UNKNOWN
Platform: UNKNOWN
Classifier: Programming Language :: Python :: 3
Classifier: License :: OSI Approved :: GNU Affero General Public License v3 or later (AGPLv3+)
Classifier: Operating System :: OS Independent
